<?xml version="1.0" encoding="utf-8"?>
<LanguageData>
  
  <GA.HookupChanceChaser>Chaser</GA.HookupChanceChaser>
  <GA.TransSex>{INITIATOR_nameDef} believes {RECIPIENT_nameDef} is transgender.</GA.TransSex>
  <GA.PawnBelievesOtherPawnIsTransLabel>{INITIATOR_nameDef} has a suspicion about {RECIPIENT_nameDef}</GA.PawnBelievesOtherPawnIsTransLabel>

  <GA.ComeOutLabel>{INITIATOR_nameDef} came out to {RECIPIENT_nameDef}</GA.ComeOutLabel>

  <GA.Masculine>masculine</GA.Masculine>
  <GA.Feminine>feminine</GA.Feminine>
  <GA.Androgynous>androgynous</GA.Androgynous>

  <GA.SocialFightTransphobia>{PAWN1_labelShort} started a social fight with {PAWN2_labelShort} because of {PAWN1_possessive} transphobic beliefs.</GA.SocialFightTransphobia>

  <GA.FoundOutThroughChat>{RECEIVER_labelShort} was told by {TELLER_labelShort} that {GOSSIPED_labelShort} is transgender.</GA.FoundOutThroughChat>

</LanguageData>